cwinpy/__init__.py
cwinpy/_version.py
cwinpy/data.py
cwinpy/heterodyne.py
cwinpy/hierarchical.py
cwinpy/likelihood.py
cwinpy/utils.py
cwinpy/iostream/__init__.py
cwinpy/iostream/ascii.py
cwinpy/iostream/hdf5.py
cwinpy/iostream/readers.py
cwinpy/pe/__init__.py
cwinpy/pe/pe.py
cwinpy/pe/simulation.py
cwinpy/pe/testing.py
cwinpy-0.5.0.dist-info/LICENSE
cwinpy-0.5.0.dist-info/METADATA
cwinpy-0.5.0.dist-info/WHEEL
cwinpy-0.5.0.dist-info/entry_points.txt
cwinpy-0.5.0.dist-info/top_level.txt
cwinpy-0.5.0.dist-info/RECORD
