Metadata-Version: 2.1
Name: cwinpy
Version: 0.5.0
Summary: A Python module for Bayesian inferences with continuous gravitational-wave sources
Home-page: http://git.ligo.org/CW/software/cwinpy
Author: Matthew Pitkin
Author-email: matthew.pitkin@ligo.org
License: MIT
Platform: UNKNOWN
Classifier: Programming Language :: Python :: 3.6
Classifier: Programming Language :: Python :: 3.7
Requires-Dist: astropy
Requires-Dist: numpy (<1.20)
Requires-Dist: bilby (>=1.0.2)
Requires-Dist: bilby-pipe (>=1.0.2)
Requires-Dist: matplotlib
Requires-Dist: scipy
Requires-Dist: lintegrate (>=0.1.7)
Requires-Dist: lalsuite (>=6.76)
Requires-Dist: numba
Requires-Dist: gwpy (>=2.0.0)
Requires-Dist: gwosc (>=0.5.4)
Requires-Dist: pycondor
